dolphindb_notebook/__init__.py
dolphindb_notebook/__main__.py
dolphindb_notebook/creds.py
dolphindb_notebook/dolphindb.js
dolphindb_notebook/kernel.json
dolphindb_notebook/kernel.py
dolphindb_notebook/dolphindb_extension/description.yaml
dolphindb_notebook/dolphindb_extension/main.js
dolphindb_notebook/images/logo-32x32.png
dolphindb_notebook/images/logo-64x64.png
dolphindb_notebook-1.1.7.data/data/lib/python3.6/site-packages/notebook/static/components/codemirror/mode/dolphindb/dolphindb.js
dolphindb_notebook-1.1.7.data/data/share/jupyter/kernels/dolphindb/creds.py
dolphindb_notebook-1.1.7.data/data/share/jupyter/kernels/dolphindb/kernel.json
dolphindb_notebook-1.1.7.data/data/share/jupyter/kernels/dolphindb/logo-32x32.png
dolphindb_notebook-1.1.7.data/data/share/jupyter/kernels/dolphindb/logo-64x64.png
dolphindb_notebook-1.1.7.data/data/share/jupyter/nbextensions/dolphindb/description.yaml
dolphindb_notebook-1.1.7.data/data/share/jupyter/nbextensions/dolphindb/main.js
dolphindb_notebook-1.1.7.dist-info/LICENSE
dolphindb_notebook-1.1.7.dist-info/METADATA
dolphindb_notebook-1.1.7.dist-info/WHEEL
dolphindb_notebook-1.1.7.dist-info/top_level.txt
dolphindb_notebook-1.1.7.dist-info/RECORD
