Metadata-Version: 2.1
Name: dolphindb-notebook
Version: 1.1.7
Summary: A Jupyter Notebook Extension for DolphinDB.
Home-page: https://www.dolphindb.com
Author: DolphinDB, Inc.
Author-email: support@dolphindb.com
License: DolphinDB
Download-URL: https://www.dolphindb.com
Keywords: IPython,Jupyter,notebook,DolphinDB
Platform: Any
Requires: jupyter_nbextensions_configurator
Requires: widgetsnbextension
Requires: metakernel
Requires: jupyter_client
Requires: ipykernel
Requires: dolphindb
Requires: tabulate
Requires: matplotlib
Requires: flask
Requires: mplfinance
Requires-Dist: jupyter-nbextensions-configurator
Requires-Dist: widgetsnbextension
Requires-Dist: metakernel
Requires-Dist: jupyter-client
Requires-Dist: ipykernel
Requires-Dist: dolphindb
Requires-Dist: tabulate
Requires-Dist: matplotlib
Requires-Dist: flask
Requires-Dist: mplfinance
